{
  "subpart_index": 0, 
  "solution": {
    "text": "<div>Given pair of equations are:</div><div>_{i}_x + _{j}_y = _{k}_ and _{j}_x + _{i}_y = _{l}_.</div><div>_{i}_x + _{j}_y - _{k}_ = 0 -------(1)</div><div>_{j}_x + _{i}_y - _{l}_ = 0 -------(2)</div><div>Comparing with general equations, we get:</div><div>\\(a_1 = _{i}_ ,a_2 = _{j}_ ,b_1 = _{j}_ ,b_2 = _{i}_\\)</div><div>Here, </div><div>\\({a_1\\over a_2} \\neq {b_1\\over b_2}\\)</div><div>Hence, given pair of equations have unique solution</div>"
  }, 
  "content": {
    "text": "<div>Check whether the following pair of equation has unique solution, no solution or infinitely many solution.</div><div>_{i}_x + _{j}_y = _{k}_ and _{j}_x + _{i}_y = _{l}_.</div>"
  }, 
  "variable_constraints": {
    "i": {
      "options": [
        2, 
        3, 
        5, 
        9, 
        4, 
        8, 
        6
      ]
    }, 
    "k": {
      "range": {
        "include": [
          [
            20, 
            40
          ]
        ]
      }
    }, 
    "j": {
      "options": [
        6, 
        8, 
        2, 
        4, 
        6, 
        4, 
        7
      ]
    }, 
    "l": {
      "range": {
        "include": [
          [
            15, 
            38
          ]
        ]
      }
    }
  }, 
  "type": 1, 
  "options": {
    "incorrect": [
      {
        "text": "No solution"
      }, 
      {
        "text": "Infinitely many solutions"
      }
    ], 
    "correct": {
      "text": "Unique solution"
    }
  }
}