{
  "subpart_index": 0, 
  "solution": {
    "text": "<div> Since Area is constant, Length and Breadth are inversely proportional. L \\(\\times\\) B = A = K</div><div>Therefore, taking area constant, K = _{{10*j}}_ \\(\\times\\) _{{5*k}}_  = _{{50*j*k}}_ cm\\(^2\\)</div><div> Hence, if Length = _{{10*k}}_ cm</div><div>Breadth =\\( \\frac {_{{50*j*k}}_}{_{{10*k}}_}\\)</div><div>\\(\\Rightarrow\\) Breadth = _{{5*j}}_ cm</div>"
  }, 
  "content": {
    "text": "The length and breadth of a given rectangle are _{{10*j}}_ and _{{5*k}}_ cm. Given that the area remains constant find the breadth of the rectangle when length is _{{10*k}}_ cm."
  }, 
  "variable_constraints": {
    "k": {
      "range": {
        "include": [
          [
            2, 
            5
          ]
        ]
      }
    }, 
    "j": {
      "range": {
        "include": [
          [
            5, 
            10
          ]
        ]
      }
    }
  }, 
  "answer": {
    "value": "_{{5*j}}_"
  }, 
  "type": 3, 
  "unit": "cm"
}