{
  "subpart_index": 3, 
  "solution": {
    "text": "<div>The number of oscillations per second is called the frequency of oscillation.</div><div>Number of oscillations in one second \\(=_{{j*k}}_\\)</div><div>Therefore, frequency \\(=_{{j*k}}_\\,Hz\\)</div><div></div>"
  }, 
  "content": {
    "text": "If an object oscillates \\(_{{j*k}}_\\) times in one second, what is its frequency?"
  }, 
  "variable_constraints": {
    "k": {}, 
    "j": {}
  }, 
  "answer": {
    "value": "_{{j*k}}_"
  }, 
  "type": 3, 
  "unit": "\\(Hz\\)"
}