{
  "questions": [
    {
      "subparts": [
        {
          "hint": null, 
          "solution": {
            "text": "<div>Area of Garden = Area of Plot - Area of the House</div><div>\\(= ab - cd\\)</div><div>\\(= (4830 - 56(17)) m^2\\)</div><div>\\(=3878 m^2\\)</div>", 
            "img_url": null, 
            "img": null
          }, 
          "subpart_index": 0, 
          "content": {
            "text": "Kshitij is looking to landscape his garden. He made a diagram of his house (grey colour) but forgot to mention the exact dimensions of the garden area. You are the engineer in charge of the project. Can you use the information given below to calculate the area of the garden? a = 105 m, b = 46 m, c = 56 m, d = 17 m", 
            "img_url": "/secure-static/c3R1dGlfcnVwYXJlbDpodHRwOi8vMTAuMTc2LjcuMjUyOjk4NzgvcXVlc3Rpb25zL3Jhdy8xLzEvOC8xLzIvaW1nLzE1LnBuZzo5SUIyckhJUGE2ZjcyTGlNWG9UQ2NXdUVrSE0/", 
            "img": "15.png"
          }, 
          "answer": {
            "tolerance": null, 
            "value": "3878"
          }, 
          "type": 3, 
          "unit": "\\(m^2\\)"
        }
      ], 
      "pk": 18, 
      "container": {
        "content": null, 
        "subparts": [
          41
        ], 
        "hint": {
          "text": "Try subtracting areas to find the right answer", 
          "img_url": null, 
          "img": null
        }
      }
    }, 
    {
      "subparts": [
        {
          "hint": null, 
          "solution": {
            "text": "Area of a square = \\(side^2 = 25 cm^2\\)", 
            "img_url": null, 
            "img": null
          }, 
          "subpart_index": 0, 
          "content": {
            "text": "In the square below, a=5 cm", 
            "img_url": "/secure-static/c3R1dGlfcnVwYXJlbDpodHRwOi8vMTAuMTc2LjcuMjUyOjk4NzgvcXVlc3Rpb25zL3Jhdy8xLzEvOC8xLzIvaW1nLzEucG5nOi1aTEZOQXJlakVtVWdhZ3NTc2tSOHdleWI1SQ/", 
            "img": "1.png"
          }, 
          "answer": {
            "tolerance": null, 
            "value": "25"
          }, 
          "type": 3, 
          "unit": "\\(cm^2\\)"
        }, 
        {
          "hint": null, 
          "solution": {
            "text": "Area of a rectangle = length \\(\\times\\) breadth \\(= 120 cm^2\\)", 
            "img_url": null, 
            "img": null
          }, 
          "subpart_index": 1, 
          "content": {
            "text": "In the rectangle below, \\(a=12 cm\\), \\(b=10 cm\\)", 
            "img_url": "/secure-static/c3R1dGlfcnVwYXJlbDpodHRwOi8vMTAuMTc2LjcuMjUyOjk4NzgvcXVlc3Rpb25zL3Jhdy8xLzEvOC8xLzIvaW1nLzIucG5nOlFURS02NlU2QTZUMC1kTU43b3drUEdoRFlSbw/", 
            "img": "2.png"
          }, 
          "answer": {
            "tolerance": null, 
            "value": "120"
          }, 
          "type": 3, 
          "unit": "\\(cm^2\\)"
        }, 
        {
          "hint": null, 
          "solution": {
            "text": "<div>Area of a circle = \\(\\pi \\times radius^2\\)</div><div>=\\(1134.57 m^2\\)</div>", 
            "img_url": null, 
            "img": null
          }, 
          "subpart_index": 2, 
          "content": {
            "text": "In the circle below, \\(r=19 m\\)", 
            "img_url": "/secure-static/c3R1dGlfcnVwYXJlbDpodHRwOi8vMTAuMTc2LjcuMjUyOjk4NzgvcXVlc3Rpb25zL3Jhdy8xLzEvOC8xLzIvaW1nLzMucG5nOkducEpjaVFmdVRTbHlWRU1jOTU2Y3lRekExZw/", 
            "img": "3.png"
          }, 
          "answer": {
            "tolerance": 0.05, 
            "value": "1134.57"
          }, 
          "type": 3, 
          "unit": "\\(m^2\\)"
        }, 
        {
          "hint": null, 
          "solution": {
            "text": "<div>Area of a triangle \\(= \\frac 12 \\times base\\times height\\)</div><div>\\(= 131.25 mm^2\\)</div>", 
            "img_url": null, 
            "img": null
          }, 
          "subpart_index": 3, 
          "content": {
            "text": "In the triangle below, \\(a=15 mm\\), \\(h = 17.5 mm\\)", 
            "img_url": "/secure-static/c3R1dGlfcnVwYXJlbDpodHRwOi8vMTAuMTc2LjcuMjUyOjk4NzgvcXVlc3Rpb25zL3Jhdy8xLzEvOC8xLzIvaW1nLzQucG5nOmxETGtuWF95cDZZd3RvTThTaWI5Sy1UeTFrbw/", 
            "img": "4.png"
          }, 
          "answer": {
            "tolerance": null, 
            "value": "131.25"
          }, 
          "type": 3, 
          "unit": "\\(mm^2\\)"
        }, 
        {
          "hint": null, 
          "solution": {
            "text": "<div>Area of the polygon = Area of square (1) + Area of triangle (2) + Area of square (3)</div><div>\\(= (a \\times b) + (\\frac 12 \\times e \\times d) + (b-d) \\times e\\)</div><div>\\(= 36 + 4.5 + 9\\)</div><div>= \\(49.5 cm^2\\)</div>", 
            "img_url": "/secure-static/c3R1dGlfcnVwYXJlbDpodHRwOi8vMTAuMTc2LjcuMjUyOjk4NzgvcXVlc3Rpb25zL3Jhdy8xLzEvOC8xLzIvaW1nLzVfc29sLnBuZzp0NVhTWGMzWnh4bU9ob2FrUEpZdDN0VVV3NGs/", 
            "img": "5_sol.png"
          }, 
          "subpart_index": 4, 
          "content": {
            "text": "In the polygon below, \\(a=6 cm\\), \\(b=6 cm\\), \\(c=9 cm\\), \\(d=3 cm\\), \\(e=3 cm\\)", 
            "img_url": "/secure-static/c3R1dGlfcnVwYXJlbDpodHRwOi8vMTAuMTc2LjcuMjUyOjk4NzgvcXVlc3Rpb25zL3Jhdy8xLzEvOC8xLzIvaW1nLzUucG5nOkFUbjBkNlUtaHByVTRESXdFYnR0VjlRMkZBUQ/", 
            "img": "5.png"
          }, 
          "answer": {
            "tolerance": null, 
            "value": "49.5"
          }, 
          "type": 3, 
          "unit": "\\(cm^2\\)"
        }, 
        {
          "hint": null, 
          "solution": {
            "text": "<div>Area of the polygon = Area Of Trapezium (1) + Area of Rectangle (2)</div><div>\\(= (\\frac 12 \\times (a+b) \\times c) + (b \\times (h-c))\\)</div><div>\\(= (\\frac 12 \\times 53 \\times 13) + (39 \\times 13)\\)</div><div>=\\(851.5 dm^2\\)</div>", 
            "img_url": "/secure-static/c3R1dGlfcnVwYXJlbDpodHRwOi8vMTAuMTc2LjcuMjUyOjk4NzgvcXVlc3Rpb25zL3Jhdy8xLzEvOC8xLzIvaW1nLzZfc29sLnBuZzowZ3g1VElqeUQ1c0pYejRIVmFCakJNTkJJMzQ/", 
            "img": "6_sol.png"
          }, 
          "subpart_index": 5, 
          "content": {
            "text": "In the polygon below, a=14 dm, b=39 dm, c= 13 dm, h= 26 dm", 
            "img_url": "/secure-static/c3R1dGlfcnVwYXJlbDpodHRwOi8vMTAuMTc2LjcuMjUyOjk4NzgvcXVlc3Rpb25zL3Jhdy8xLzEvOC8xLzIvaW1nLzYucG5nOmF6WmJJRlVyaWJydWlsZlcxMG9CQ2lyeXN6RQ/", 
            "img": "6.png"
          }, 
          "answer": {
            "tolerance": null, 
            "value": "851.5"
          }, 
          "type": 3, 
          "unit": "\\(dm^2\\)"
        }, 
        {
          "hint": null, 
          "solution": {
            "text": "<div>Area of a parallelogram = \\(Base \\times Height\\)</div><div>\\(= 18 \\times 9 cm^2\\)</div><div>\\(= 162 cm^2\\)</div>", 
            "img_url": null, 
            "img": null
          }, 
          "subpart_index": 6, 
          "content": {
            "text": "In the parallelogram below, a=18 cm, h=9 cm", 
            "img_url": "/secure-static/c3R1dGlfcnVwYXJlbDpodHRwOi8vMTAuMTc2LjcuMjUyOjk4NzgvcXVlc3Rpb25zL3Jhdy8xLzEvOC8xLzIvaW1nLzcucG5nOmJyVU90dko0amRubkViZGczZlVlbmRMMmlIQQ/", 
            "img": "7.png"
          }, 
          "answer": {
            "tolerance": null, 
            "value": "162"
          }, 
          "type": 3, 
          "unit": "\\(cm^2\\)"
        }, 
        {
          "hint": null, 
          "solution": {
            "text": "<div>Area of Quadrilateral = Area of Triangle (1) + Area of Triangle (2)</div><div>\\(= \\frac 12 \\times h_ 1 \\times d + \\frac 12 \\times h_ 2 \\times d\\)</div><div>\\(= (\\frac 12 \\times 5 \\times 20) + (\\frac 12 \\times 10 \\times 20)\\)</div><div>=\\(150 cm^2\\)</div>", 
            "img_url": "/secure-static/c3R1dGlfcnVwYXJlbDpodHRwOi8vMTAuMTc2LjcuMjUyOjk4NzgvcXVlc3Rpb25zL3Jhdy8xLzEvOC8xLzIvaW1nLzhfc29sLnBuZzpCU2o3SkpEXy1jZ1N5UEwwd0d1OXZoYkF6M2c/", 
            "img": "8_sol.png"
          }, 
          "subpart_index": 7, 
          "content": {
            "text": "In the quadrilateral below, \\(h1=5 cm\\), \\(h2=10 cm\\), \\(d=20 cm\\)", 
            "img_url": "/secure-static/c3R1dGlfcnVwYXJlbDpodHRwOi8vMTAuMTc2LjcuMjUyOjk4NzgvcXVlc3Rpb25zL3Jhdy8xLzEvOC8xLzIvaW1nLzgucG5nOkR0OVZiU3BELTk2cFFTZ3JsUmx6ZXEtT0Nzdw/", 
            "img": "8.png"
          }, 
          "answer": {
            "tolerance": null, 
            "value": "150"
          }, 
          "type": 3, 
          "unit": "\\(cm^2\\)"
        }, 
        {
          "hint": null, 
          "solution": {
            "text": "<div>Area of Polygon = Area of Triangle (1) + Area of Trapezium (2) + Area of Triangle (3) + Area of Triangle (4) + Area of Triangle (5)</div><div>\\(= (\\frac 12 \\times a \\times b) + (\\frac 12 (b + e)(c + d)) + (\\frac 12 \\times e \\times f) + (\\frac 12 \\times g \\times (d+f)) + (\\frac 12 \\times (a+c) \\times g)\\)</div><div>\\(= (\\frac 12 \\times 40 \\times 41) + (\\frac 12 \\times 91 \\times 61) + (\\frac 12 \\times 50 \\times 30) + (\\frac 12 \\times 40 \\times 50) + (\\frac 12 \\times 81 \\times 40)\\)</div><div>\\(= 820 + 2775.5 + 750 + 1000 + 1620 \\)</div><div>\\(=6965.5 cm^2\\)</div>", 
            "img_url": "/secure-static/c3R1dGlfcnVwYXJlbDpodHRwOi8vMTAuMTc2LjcuMjUyOjk4NzgvcXVlc3Rpb25zL3Jhdy8xLzEvOC8xLzIvaW1nLzlfc29sLnBuZzpRZW9zMndEY1VHZVZYZ1pnaldKcnBMdDNObmc/", 
            "img": "9_sol.png"
          }, 
          "subpart_index": 8, 
          "content": {
            "text": "In the polygon below, a=40 cm, b=41 cm, c=41 cm, d=20 cm, e=50 cm, f=30 cm, g=40 cm", 
            "img_url": "/secure-static/c3R1dGlfcnVwYXJlbDpodHRwOi8vMTAuMTc2LjcuMjUyOjk4NzgvcXVlc3Rpb25zL3Jhdy8xLzEvOC8xLzIvaW1nLzkucG5nOnhfbDIwM1VXRm1FOVhMaEgzbFk3X281RlYxaw/", 
            "img": "9.png"
          }, 
          "answer": {
            "tolerance": null, 
            "value": "6965.5"
          }, 
          "type": 3, 
          "unit": "\\(cm^2\\)"
        }, 
        {
          "hint": null, 
          "solution": {
            "text": "<div>Area of Polygon = Area of Trapezium (1) + Area of Trapezium (2)</div><div>= Area of Trapezium \\(\\times 2\\)</div><div>\\(= \\frac 12 (a+c)(h) \\times 2\\)</div><div>\\(= \\frac 12 (18 + 24)(12) \\times 2\\)</div><div>\\(= 504 mm^2\\)</div>", 
            "img_url": "/secure-static/c3R1dGlfcnVwYXJlbDpodHRwOi8vMTAuMTc2LjcuMjUyOjk4NzgvcXVlc3Rpb25zL3Jhdy8xLzEvOC8xLzIvaW1nLzEwX3NvbC5wbmc6aDZsSnFLN1U2S0J0Mm54amdVbkY0ejF0N3o4/", 
            "img": "10_sol.png"
          }, 
          "subpart_index": 9, 
          "content": {
            "text": "In the polygon below, a=18 mm, h=12 mm, c=24 mm", 
            "img_url": "/secure-static/c3R1dGlfcnVwYXJlbDpodHRwOi8vMTAuMTc2LjcuMjUyOjk4NzgvcXVlc3Rpb25zL3Jhdy8xLzEvOC8xLzIvaW1nLzEwLnBuZzo2MGlQZUVpLXl3NDVCeG52OU9ENUFQczlVNW8/", 
            "img": "10.png"
          }, 
          "answer": {
            "tolerance": null, 
            "value": "504"
          }, 
          "type": 3, 
          "unit": "\\(mm^2\\)"
        }
      ], 
      "pk": 17, 
      "container": {
        "content": {
          "text": "Find the area of the shapes below:", 
          "img_url": null, 
          "img": null
        }, 
        "subparts": [
          1, 
          3, 
          5, 
          7, 
          9, 
          11, 
          13, 
          15, 
          17, 
          19
        ], 
        "hint": {
          "text": "<div>Observe the shapes carefully and see if you can break them down into smaller shapes to make calculating the areas easier. Remember the following formulas:</div><div>Area of Rectangle: \\(length \\times breadth\\)</div><div>Area of Square: \\(length^2\\)</div><div>Area of a Triangle: \\(\\frac 12 \\times base \\times height\\)</div><div>Area of Parallelogram: \\(base \\times height\\)</div><div>Area of Trapezium: \\(\\frac 12 \\times (a+b) \\times h\\)</div>", 
          "img_url": null, 
          "img": null
        }
      }
    }, 
    {
      "subparts": [
        {
          "hint": null, 
          "solution": {
            "text": "<div>Area of school floor \\(= 5980 m^2\\)</div><div>Area of each tile = \\(Base \\times height = 20 \\times 13 = 260 cm^2\\)</div><div>Since the tiles can be perfectly broken into smaller parts, the number of tiles required is the area of the floor divided by the area of each tile. Also, remember that \\(1m^2 = 10000 cm^2\\)</div><div>Therefore, Number of tiles \\(= \\frac{5980 \\times 10000}{260} = 230000\\)</div>", 
            "img_url": null, 
            "img": null
          }, 
          "subpart_index": 0, 
          "content": {
            "text": "The area of your school library floor is \\(5980 m^2\\). You are asked to use tiles in the shape of a parallelogram with a base of 20 cm and a height of 13 cm to cover the floor. How many such tiles will you need to purchase? You can break the tiles in any way to cover the entire floor.", 
            "img_url": null, 
            "img": null
          }, 
          "answer": {
            "tolerance": null, 
            "value": "230000"
          }, 
          "type": 3, 
          "unit": null
        }
      ], 
      "pk": 19, 
      "container": {
        "content": null, 
        "subparts": [
          42
        ], 
        "hint": {
          "text": "Start by finding the area of each tile.", 
          "img_url": null, 
          "img": null
        }
      }
    }, 
    {
      "subparts": [
        {
          "hint": null, 
          "solution": {
            "text": "<div>Given the area \\(= \\frac 12 \\times Width \\times\\) (Sum of parallel sides)</div><div>\\(= \\frac 12 \\times 24 \\times (21 +\\) River Side Length\\()\\)</div><div>Therefore River Side Length = \\(\\frac{972}{12} - 21\\)</div><div>\\(= 60 m\\)</div>", 
            "img_url": null, 
            "img": null
          }, 
          "subpart_index": 0, 
          "content": {
            "text": "Hussain bought a plot of agricultural land which is in the shape of a trapezium (see below). The area of the land is \\(972 m^2\\), the side parallel to the road is 21 metres and the width of the field is 24 metres. How long is the side parallel to the river?", 
            "img_url": "/secure-static/c3R1dGlfcnVwYXJlbDpodHRwOi8vMTAuMTc2LjcuMjUyOjk4NzgvcXVlc3Rpb25zL3Jhdy8xLzEvOC8xLzIvaW1nLzE2LnBuZzo2azlwcTNaWlFzVlRpSUVmcXd5a19FVS1qUVE/", 
            "img": "16.png"
          }, 
          "answer": {
            "tolerance": null, 
            "value": "60"
          }, 
          "type": 3, 
          "unit": "metres"
        }
      ], 
      "pk": 20, 
      "container": {
        "content": null, 
        "subparts": [
          43
        ], 
        "hint": {
          "text": "The area of a trapezium is \\(\\frac 12 \\times Height \\times\\) (Sum of parallel sides)", 
          "img_url": null, 
          "img": null
        }
      }
    }
  ], 
  "answers": [
    [
      {
        "correct": true, 
        "value": "3878"
      }
    ], 
    [
      {
        "correct": true, 
        "value": "25"
      }, 
      {
        "correct": true, 
        "value": "120"
      }, 
      {
        "correct": false, 
        "value": "1134.11495"
      }, 
      {
        "correct": true, 
        "value": "131.25"
      }, 
      {
        "correct": true, 
        "value": "49.5"
      }, 
      {
        "correct": true, 
        "value": "851.5"
      }, 
      {
        "correct": true, 
        "value": "162"
      }, 
      {
        "correct": true, 
        "value": "150"
      }, 
      {
        "correct": true, 
        "value": "6965.5"
      }, 
      {
        "correct": true, 
        "value": "504"
      }
    ], 
    [
      {
        "correct": true, 
        "value": "230000"
      }
    ], 
    [
      {
        "correct": true, 
        "value": "60"
      }
    ]
  ]
}