{
  "questions": [
    {
      "subparts": [
        {
          "hint": {
            "text": "<div>Terms common to both the numerator and denominator can be cancelled.</div><div>For example : </div><div>\\(\\frac{x^3abc}{xab},\\,\\)where x, a, b, c are non-zero integers; can be expressed as</div><div>\\('x^2c'\\,\\)because \\('xab'\\,\\)is the common term for the numerator and denominator.</div> ", 
            "img_url": null, 
            "img": null
          }, 
          "solution": {
            "text": "<div>\\(\\frac{468x^3y^3z^3a^3b^3c^3+18x^2yx+108xy^2z+117xyz^2}{9xyz}\\)</div><div>Taking \\(9xyz\\,\\)common in the numerator,</div><div>\\(=\\frac{9xyz(52x^2y^2z^2a^3b^3c^3)+9xyz(2x)+9xyz(12y)+9xyz(13z)}{9xyz}\\)</div><div>Dividing numerator and denominator by \\(9xyz\\),</div><div>\\(=52x^2y^2z^2a^3b^3c^3+2x+12y+13z\\)</div>", 
            "img_url": null, 
            "img": null
          }, 
          "subpart_index": 0, 
          "content": {
            "text": "\\(\\frac{468x^3y^3z^3a^3b^3c^3+18x^2yz+108xy^2z+117xyz^2}{9xyz}\\)", 
            "img_url": null, 
            "img": null
          }, 
          "type": 1, 
          "options": {
            "incorrect": [
              {
                "text": "\\(52xyza^3b^3c^3+2x+12y+13z\\)", 
                "img_url": null, 
                "img": null
              }, 
              {
                "text": "\\(52a^3b^3c^3+2x+12y+13z\\)", 
                "img_url": null, 
                "img": null
              }, 
              {
                "text": "\\(52x^2y^2z^2+2x+12y+13z\\)", 
                "img_url": null, 
                "img": null
              }
            ], 
            "use_dropdown_widget": false, 
            "order": [
              2, 
              1, 
              0, 
              3
            ], 
            "correct": {
              "text": "\\(52x^2y^2z^2a^3b^3c^3+2x+12y+13z\\)", 
              "img_url": null, 
              "img": null
            }
          }
        }, 
        {
          "hint": {
            "text": "<div>Terms common to both the numerator and denominator can be cancelled.</div><div>For example : </div><div>\\(\\frac{x^3abc}{xab},\\,\\)where x, a, b, c are non-zero integers; can be expressed as</div><div>\\('x^2c'\\,\\)because \\('xab'\\,\\)is the common term for the numerator and denominator.</div> ", 
            "img_url": null, 
            "img": null
          }, 
          "solution": {
            "text": "<div>\\(\\frac{20x^3y-19xy*4}{-xy}\\)</div><div>Taking \\(-xy\\,\\)common from the numerator,</div><div>\\(=\\frac{-xy(19y^3-20x^2)}{-xy}\\)</div><div>Dividing numerator and denominator by \\(-xy\\),</div><div>\\(=19y^3-20x^2\\)</div>", 
            "img_url": null, 
            "img": null
          }, 
          "subpart_index": 1, 
          "content": {
            "text": "\\(\\frac{20x^3y-19xy^4}{-xy}\\)", 
            "img_url": null, 
            "img": null
          }, 
          "type": 1, 
          "options": {
            "incorrect": [
              {
                "text": "\\(19x^3-20y^2\\)", 
                "img_url": null, 
                "img": null
              }, 
              {
                "text": "\\(19y^2-20x^3\\)", 
                "img_url": null, 
                "img": null
              }, 
              {
                "text": "\\(19xy^3-20x^2y\\)", 
                "img_url": null, 
                "img": null
              }
            ], 
            "use_dropdown_widget": false, 
            "order": [
              2, 
              0, 
              1, 
              3
            ], 
            "correct": {
              "text": "\\(19y^3-20x^2\\)", 
              "img_url": null, 
              "img": null
            }
          }
        }, 
        {
          "hint": {
            "text": "<div>Terms common to both the numerator and denominator can be cancelled.</div><div>For example : </div><div>\\(\\frac{x^3abc}{xab},\\,\\)where x, a, b, c are non-zero integers; can be expressed as</div><div>\\('x^2c'\\,\\)because \\('xab'\\,\\)is the common term for the numerator and denominator.</div> ", 
            "img_url": null, 
            "img": null
          }, 
          "solution": {
            "text": "<div>\\(\\frac{5a^4+9a^3+7a^2+3a}{3a}\\)</div><div>Taking \\(3a\\,\\)common from the numerator,</div><div>\\(=\\frac{3a(\\frac{5a^3}3 + 3a^2 + \\frac{7a}3 + 1)}{3a}\\)</div><div>Dividing numerator and denominator by \\(3a\\),</div><div>\\(=\\frac{5a^3}3 + 3a^2 + \\frac{7a}3 + 1\\)</div>", 
            "img_url": null, 
            "img": null
          }, 
          "subpart_index": 2, 
          "content": {
            "text": "\\(\\frac{5a^4+9a^3+7a^2+3a}{3a}\\)", 
            "img_url": null, 
            "img": null
          }, 
          "type": 1, 
          "options": {
            "incorrect": [
              {
                "text": "\\(\\frac{5a^2}3 + 3a + \\frac73 + \\frac1a\\)", 
                "img_url": null, 
                "img": null
              }, 
              {
                "text": "\\(\\frac{5a^4}3 + 3a^3 + \\frac{7a^2}3 + a\\)", 
                "img_url": null, 
                "img": null
              }, 
              {
                "text": "\\(\\frac{5a^3}3 + 9a^2 + \\frac{7a}3 + 1\\)", 
                "img_url": null, 
                "img": null
              }
            ], 
            "use_dropdown_widget": false, 
            "order": [
              3, 
              2, 
              1, 
              0
            ], 
            "correct": {
              "text": "\\(\\frac{5a^3}3 + 3a^2 + \\frac{7a}3 + 1\\)", 
              "img_url": null, 
              "img": null
            }
          }
        }
      ], 
      "pk": 114, 
      "container": {
        "content": {
          "text": "Divide the following expressions : ", 
          "img_url": null, 
          "img": null
        }, 
        "subparts": [
          151, 
          152, 
          153
        ], 
        "hint": null
      }
    }, 
    {
      "subparts": [
        {
          "hint": {
            "text": "<div>Terms common to both the numerator and denominator can be cancelled.</div><div>For example : </div><div>\\(\\frac{x^3abc}{xab},\\,\\)where x, a, b, c are non-zero integers; can be expressed as</div><div>\\('x^2c'\\,\\)because \\('xab'\\,\\)is the common term for the numerator and denominator.</div> ", 
            "img_url": null, 
            "img": null
          }, 
          "solution": {
            "text": "<div>\\(\\frac{25x^2+(60-15)x-36}{5x-3}\\)</div><div>\\(=\\frac{25x^2+60x-15x-36}{5x-3}\\)</div><div>Taking \\(5x\\,\\) and \\(3\\) commmon,</div><div>\\(=\\frac{5x(5x+12)-3(5x+12)}{5x-3}\\)</div><div>\\(=\\frac{(5x-3)(5x+12)}{5x-3}\\)</div><div>Dividing the numerator and denominator by \\(5x-3\\),</div><div>\\(=5x+12\\)</div>", 
            "img_url": null, 
            "img": null
          }, 
          "subpart_index": 0, 
          "content": {
            "text": "\\(\\frac{25x^2+(60-15)x-36}{5x-3}\\)", 
            "img_url": null, 
            "img": null
          }, 
          "type": 1, 
          "options": {
            "incorrect": [
              {
                "text": "\\(5+12x\\)", 
                "img_url": null, 
                "img": null
              }, 
              {
                "text": "\\(8x-4\\)", 
                "img_url": null, 
                "img": null
              }, 
              {
                "text": "\\(4-8x\\)", 
                "img_url": null, 
                "img": null
              }
            ], 
            "use_dropdown_widget": false, 
            "order": [
              3, 
              2, 
              1, 
              0
            ], 
            "correct": {
              "text": "\\(5x+12\\)", 
              "img_url": null, 
              "img": null
            }
          }
        }, 
        {
          "hint": {
            "text": "<div>Terms common to both the numerator and denominator can be cancelled.</div><div>For example : </div><div>\\(\\frac{x^3abc}{xab},\\,\\)where x, a, b, c are non-zero integers; can be expressed as</div><div>\\('x^2c'\\,\\)because \\('xab'\\,\\)is the common term for the numerator and denominator.</div> ", 
            "img_url": null, 
            "img": null
          }, 
          "solution": {
            "text": "<div>\\(\\frac{18t^4-18s^4}{t-s}\\)</div><div>Consider that LHS \\(=18t^4-18s^4\\)</div><div>\\(=18(t^4-s^4)\\)</div><div>\\(=18(t^2-s^2)(t^2+s^2)\\,\\)[Using identity \\(a^2-b^2=(a-b)(a+b)\\)]</div><div>\\(=18(t-s)(t+s)(t^2+s^2)\\,\\)[Using identity \\(a^2-b^2=(a-b)(a+b)\\)]</div><div>Therefore,</div><div>\\(\\frac{18t^4-18s^4}{t-s}\\)</div><div>\\(=\\frac{18(t-s)(t+s)(t^2+s^2)}{t-s}\\)</div><div>Dividing numerator and denominator by \\((t-s)\\),</div><div>\\(=18(t+s)(t^2+s^2)\\)</div>", 
            "img_url": null, 
            "img": null
          }, 
          "subpart_index": 1, 
          "content": {
            "text": "\\(\\frac{18t^4-18s^4}{t-s}\\)", 
            "img_url": null, 
            "img": null
          }, 
          "type": 1, 
          "options": {
            "incorrect": [
              {
                "text": "\\(18(t-s)(t^2+s^2)\\)", 
                "img_url": null, 
                "img": null
              }, 
              {
                "text": "\\(18(t+s)(t^2-s^2)\\)", 
                "img_url": null, 
                "img": null
              }, 
              {
                "text": "\\(18(t-s)(t^2-s^2)\\)", 
                "img_url": null, 
                "img": null
              }
            ], 
            "use_dropdown_widget": false, 
            "order": [
              1, 
              0, 
              2, 
              3
            ], 
            "correct": {
              "text": "\\(18(t+s)(t^2+s^2)\\)", 
              "img_url": null, 
              "img": null
            }
          }
        }, 
        {
          "hint": {
            "text": "<div>Terms common to both the numerator and denominator can be cancelled.</div><div>For example : </div><div>\\(\\frac{x^3abc}{xab},\\,\\)where x, a, b, c are non-zero integers; can be expressed as</div><div>\\('x^2c'\\,\\)because \\('xab'\\,\\)is the common term for the numerator and denominator.</div> ", 
            "img_url": null, 
            "img": null
          }, 
          "solution": {
            "text": "<div>\\(\\frac{a^{8x}+a^{4x}b^{4y}+b^{8y}}{a^{4x}+a^{2x}b^{2y}+b^{4y}}\\)</div><div>Consider the LHS = \\(a^{8x}+a^{4x}b^{4y}+b^{8y}\\)</div><div>\\(=(a^{4x})^2+2a^{4x}b^{4y}+(b^{4y})^2-a^{4x}b^{4y}\\,\\)[Adding and subtracting \\(a^{4x}b^{4y}\\)]</div><div>\\(=(a^{4x}+b^{4y})^2-(a^{2x}b^{2y})^2\\,\\)[Using identity \\(a^2+2ab+b^2=(a+b)^2\\)]</div><div>\\(=(a^{4x}+b^{4y}-a^{2x}b^{2y})(a^{4x}+b^{4y}+a^{2x}b^{2y})\\,\\)[Using identity \\(a^2-b^2=(a-b)(a+b)\\)]</div><div>Therefore,</div><div>\\(\\frac{a^{8x}+a^{4x}b^{4y}+b^{8y}}{a^{4x}+a^{2x}b^{2y}+b^{4y}}\\)</div><div>\\(=\\frac{(a^{4x}+b^{4y}-a^{2x}b^{2y})(a^{4x}+b^{4y}+a^{2x}b^{2y})}{a^{4x}+a^{2x}b^{2y}+b^{4y}}\\)</div><div>\\(=a^{4x}+b^{4y}-a^{2x}b^{2y}\\)</div>", 
            "img_url": null, 
            "img": null
          }, 
          "subpart_index": 2, 
          "content": {
            "text": "\\(\\frac{a^{8x}+a^{4x}b^{4y}+b^{8y}}{a^{4x}+a^{2x}b^{2y}+b^{4y}}\\)", 
            "img_url": null, 
            "img": null
          }, 
          "type": 1, 
          "options": {
            "incorrect": [
              {
                "text": "\\(a^{4x}+b^{4y}+a^{2x}b^{2y}\\)", 
                "img_url": null, 
                "img": null
              }, 
              {
                "text": "\\(a^{2x}+b^{2y}-a^{x}b^{y}\\)", 
                "img_url": null, 
                "img": null
              }, 
              {
                "text": "\\(a^{2x}+b^{2y}+a^{x}b^{y}\\)", 
                "img_url": null, 
                "img": null
              }
            ], 
            "use_dropdown_widget": false, 
            "order": [
              3, 
              1, 
              2, 
              0
            ], 
            "correct": {
              "text": "\\(a^{4x}+b^{4y}-a^{2x}b^{2y}\\)", 
              "img_url": null, 
              "img": null
            }
          }
        }
      ], 
      "pk": 115, 
      "container": {
        "content": {
          "text": "Divide the following expressions using the factorisation method: ", 
          "img_url": null, 
          "img": null
        }, 
        "subparts": [
          161, 
          162, 
          163
        ], 
        "hint": null
      }
    }, 
    {
      "subparts": [
        {
          "hint": {
            "text": "<div>Terms common to both the numerator and denominator can be cancelled.</div><div>For example : </div><div>\\(\\frac{x^3abc}{xab},\\,\\)where x, a, b, c are non-zero integers; can be expressed as</div><div>\\('x^2c'\\,\\)because \\('xab'\\,\\)is the common term for the numerator and denominator.</div> ", 
            "img_url": null, 
            "img": null
          }, 
          "solution": {
            "text": "<div>\\(\\frac{60t^3}{40t}\\)</div><div>Taking \\(20t\\,\\)common in the numerator and denominator,</div><div>\\(=\\frac{(3)t^2(20t)}{(2)(20t)}\\)</div><div>Dividing numerator and denominator by \\(20t,\\)</div><div>\\(=\\frac{3t^2}2\\)</div>", 
            "img_url": null, 
            "img": null
          }, 
          "subpart_index": 0, 
          "content": {
            "text": "\\(\\frac{60t^3}{40t}\\)", 
            "img_url": null, 
            "img": null
          }, 
          "type": 1, 
          "options": {
            "incorrect": [
              {
                "text": "\\(3t^2\\)", 
                "img_url": null, 
                "img": null
              }, 
              {
                "text": "\\(\\frac{3t}2\\)", 
                "img_url": null, 
                "img": null
              }, 
              {
                "text": "\\(\\frac{t^2}2\\)", 
                "img_url": null, 
                "img": null
              }
            ], 
            "use_dropdown_widget": false, 
            "order": [
              0, 
              1, 
              3, 
              2
            ], 
            "correct": {
              "text": "\\(\\frac{3t^2}2\\)", 
              "img_url": null, 
              "img": null
            }
          }
        }, 
        {
          "hint": {
            "text": "<div>Terms common to both the numerator and denominator can be cancelled.</div><div>For example : </div><div>\\(\\frac{x^3abc}{xab},\\,\\)where x, a, b, c are non-zero integers; can be expressed as</div><div>\\('x^2c'\\,\\)because \\('xab'\\,\\)is the common term for the numerator and denominator.</div> ", 
            "img_url": null, 
            "img": null
          }, 
          "solution": {
            "text": "<div>\\(\\frac{-63x^4yz}{9x^2y}\\)</div><div>Taking \\(9x^2y\\,\\)common in the numerator and denominator,</div><div>\\(=\\frac{-7x^2z(9x^2y)}{(9x^2y)}\\)</div><div>Dividing numerator and denominator by \\(9x^2y,\\)</div><div>\\(=-7x^2z\\)</div>", 
            "img_url": null, 
            "img": null
          }, 
          "subpart_index": 1, 
          "content": {
            "text": "\\(\\frac{-63x^4yz}{9x^2y}\\)", 
            "img_url": null, 
            "img": null
          }, 
          "type": 1, 
          "options": {
            "incorrect": [
              {
                "text": "\\(\\frac{-7x^2}z\\)", 
                "img_url": null, 
                "img": null
              }, 
              {
                "text": "\\(7xz\\)", 
                "img_url": null, 
                "img": null
              }, 
              {
                "text": "\\(7x^2z\\)", 
                "img_url": null, 
                "img": null
              }
            ], 
            "use_dropdown_widget": false, 
            "order": [
              2, 
              3, 
              0, 
              1
            ], 
            "correct": {
              "text": "\\(-7x^2z\\)", 
              "img_url": null, 
              "img": null
            }
          }
        }, 
        {
          "hint": {
            "text": "<div>Terms common to both the numerator and denominator can be cancelled.</div><div>For example : </div><div>\\(\\frac{x^3abc}{xab},\\,\\)where x, a, b, c are non-zero integers; can be expressed as</div><div>\\('x^2c'\\,\\)because \\('xab'\\,\\)is the common term for the numerator and denominator.</div> ", 
            "img_url": null, 
            "img": null
          }, 
          "solution": {
            "text": "<div>\\(\\frac{288x^2ac}{4x^4a}\\)</div><div>Taking \\(4x^2a\\,\\)common in the numerator and the denominator,</div><div>\\(=\\frac{72c(4x^2a)}{x^2(4x^2a)}\\)</div><div>Dividing numerator and denominator by \\(4x^2a,\\)</div><div>\\(=\\frac{72c}{x^2}\\)</div>", 
            "img_url": null, 
            "img": null
          }, 
          "subpart_index": 2, 
          "content": {
            "text": "\\(\\frac{288x^2ac}{4x^4a}\\)", 
            "img_url": null, 
            "img": null
          }, 
          "type": 1, 
          "options": {
            "incorrect": [
              {
                "text": "\\(\\frac{72ac}{x^2}\\)", 
                "img_url": null, 
                "img": null
              }, 
              {
                "text": "\\(\\frac{72c}x\\)", 
                "img_url": null, 
                "img": null
              }, 
              {
                "text": "\\(\\frac{72}{x^2}\\)", 
                "img_url": null, 
                "img": null
              }
            ], 
            "use_dropdown_widget": false, 
            "order": [
              2, 
              3, 
              0, 
              1
            ], 
            "correct": {
              "text": "\\(\\frac{72c}{x^2}\\)", 
              "img_url": null, 
              "img": null
            }
          }
        }
      ], 
      "pk": 113, 
      "container": {
        "content": {
          "text": "Divide the following expressions : ", 
          "img_url": null, 
          "img": null
        }, 
        "subparts": [
          141, 
          142, 
          143
        ], 
        "hint": null
      }
    }, 
    {
      "subparts": [
        {
          "hint": null, 
          "solution": {
            "text": "<div>\\(10(x-2)\\)</div><div>\\(10x-(10\\times 2)\\)</div><div>\\(\\neq 10x-2\\)</div>", 
            "img_url": null, 
            "img": null
          }, 
          "subpart_index": 0, 
          "content": {
            "text": "\\(10(x-2)=10x-2\\)", 
            "img_url": null, 
            "img": null
          }, 
          "type": 1, 
          "options": {
            "incorrect": [
              {
                "text": "Correct", 
                "img_url": null, 
                "img": null
              }
            ], 
            "use_dropdown_widget": true, 
            "order": [
              1, 
              0
            ], 
            "correct": {
              "text": "Incorrect", 
              "img_url": null, 
              "img": null
            }
          }
        }, 
        {
          "hint": null, 
          "solution": {
            "text": "<div>Consider RHS</div><div>\\(=(13+2)xy\\)</div><div>\\(=13xy+2xy\\)</div><div>\\(\\neq 13x+2y\\)</div>", 
            "img_url": null, 
            "img": null
          }, 
          "subpart_index": 1, 
          "content": {
            "text": "\\(13x+2y=(13+2)xy\\)", 
            "img_url": null, 
            "img": null
          }, 
          "type": 1, 
          "options": {
            "incorrect": [
              {
                "text": "Correct", 
                "img_url": null, 
                "img": null
              }
            ], 
            "use_dropdown_widget": true, 
            "order": [
              0, 
              1
            ], 
            "correct": {
              "text": "Incorrect", 
              "img_url": null, 
              "img": null
            }
          }
        }, 
        {
          "hint": null, 
          "solution": {
            "text": "<div>Consider LHS</div><div>\\(=7x+7x\\)</div><div>\\(=14x\\)</div><div>\\(\\neq 7x^2\\)</div>", 
            "img_url": null, 
            "img": null
          }, 
          "subpart_index": 2, 
          "content": {
            "text": "\\(7x+7x=7x^2\\)", 
            "img_url": null, 
            "img": null
          }, 
          "type": 1, 
          "options": {
            "incorrect": [
              {
                "text": "Correct", 
                "img_url": null, 
                "img": null
              }
            ], 
            "use_dropdown_widget": true, 
            "order": [
              1, 
              0
            ], 
            "correct": {
              "text": "Incorrect", 
              "img_url": null, 
              "img": null
            }
          }
        }, 
        {
          "hint": null, 
          "solution": {
            "text": "<div>Consider LHS</div><div>\\(=(19-y)^2\\)</div><div>\\(=361-38y+y^2\\)</div><div>\\(\\neq 361-y^2\\)</div>", 
            "img_url": null, 
            "img": null
          }, 
          "subpart_index": 3, 
          "content": {
            "text": "\\((19-y)^2=361-y^2\\)", 
            "img_url": null, 
            "img": null
          }, 
          "type": 1, 
          "options": {
            "incorrect": [
              {
                "text": "Correct", 
                "img_url": null, 
                "img": null
              }
            ], 
            "use_dropdown_widget": true, 
            "order": [
              0, 
              1
            ], 
            "correct": {
              "text": "Incorrect", 
              "img_url": null, 
              "img": null
            }
          }
        }, 
        {
          "hint": null, 
          "solution": {
            "text": "<div>Consider LHS</div><div>\\(=\\frac{20a^2}{20a^2}\\)</div><div>\\(=1\\)</div><div>\\(\\neq 0\\)</div>", 
            "img_url": null, 
            "img": null
          }, 
          "subpart_index": 4, 
          "content": {
            "text": "\\(\\frac{20a^2}{20a^2}=0\\)", 
            "img_url": null, 
            "img": null
          }, 
          "type": 1, 
          "options": {
            "incorrect": [
              {
                "text": "Correct", 
                "img_url": null, 
                "img": null
              }
            ], 
            "use_dropdown_widget": true, 
            "order": [
              1, 
              0
            ], 
            "correct": {
              "text": "Incorrect", 
              "img_url": null, 
              "img": null
            }
          }
        }, 
        {
          "hint": null, 
          "solution": {
            "text": "<div>Consider LHS</div><div>\\(=\\frac{8}{8x+16x}\\)</div><div>\\(=\\frac{8}{8(x+2x)}\\)</div><div>\\(=\\frac1{x+2x}\\)</div>", 
            "img_url": null, 
            "img": null
          }, 
          "subpart_index": 5, 
          "content": {
            "text": "\\(\\frac{8}{8x+16x}=\\frac1{(x+2x)}\\)", 
            "img_url": null, 
            "img": null
          }, 
          "type": 1, 
          "options": {
            "incorrect": [
              {
                "text": "Incorrect", 
                "img_url": null, 
                "img": null
              }
            ], 
            "use_dropdown_widget": true, 
            "order": [
              0, 
              1
            ], 
            "correct": {
              "text": "Correct", 
              "img_url": null, 
              "img": null
            }
          }
        }
      ], 
      "pk": 118, 
      "container": {
        "content": {
          "text": "Categorise the following as correct or incorrect.", 
          "img_url": null, 
          "img": null
        }, 
        "subparts": [
          191, 
          192, 
          193, 
          194, 
          195, 
          196
        ], 
        "hint": null
      }
    }
  ], 
  "answers": [
    [
      {
        "correct": false, 
        "choice": null
      }, 
      {
        "correct": false, 
        "choice": null
      }, 
      {
        "correct": false, 
        "choice": null
      }
    ], 
    [
      {
        "correct": false, 
        "choice": null
      }, 
      {
        "correct": false, 
        "choice": null
      }, 
      {
        "correct": false, 
        "choice": null
      }
    ], 
    [
      {
        "correct": false, 
        "choice": null
      }, 
      {
        "correct": false, 
        "choice": null
      }, 
      {
        "correct": false, 
        "choice": null
      }
    ], 
    [
      {
        "correct": false, 
        "choice": null
      }, 
      {
        "correct": false, 
        "choice": null
      }, 
      {
        "correct": false, 
        "choice": null
      }, 
      {
        "correct": false, 
        "choice": null
      }, 
      {
        "correct": false, 
        "choice": null
      }, 
      {
        "correct": false, 
        "choice": null
      }
    ]
  ]
}