{
  "subpart_index": 0, 
  "solution": {
    "text": "<div>Observe the graph carefully.</div><div>The number of students lying in a particular range of marks in the table must correspond to that in the graph.</div>"
  }, 
  "content": {
    "text": "Which of these Histograms represent the below data?", 
    "img": "41.png"
  }, 
  "variable_constraints": {}, 
  "type": 1, 
  "options": {
    "incorrect": [
      {
        "img": "411.png"
      }, 
      {
        "img": "413.png"
      }, 
      {
        "img": "414.png"
      }
    ], 
    "correct": {
      "img": "412.png"
    }
  }
}